androsing/__init__.py
androsing/cli.py
androsing/core.py
androsing-1.0.0.dist-info/METADATA
androsing-1.0.0.dist-info/WHEEL
androsing-1.0.0.dist-info/entry_points.txt
androsing-1.0.0.dist-info/top_level.txt
androsing-1.0.0.dist-info/RECORD
